{
    "success": true,
    "terms": "https://currencylayer.com/terms",
    "privacy": "https://currencylayer.com/privacy",
    "timestamp": 1761841396,
    "source": "USD",
    "quotes": {
        "USDAED": 3.672499,
        "USDAFN": 66.814184,
        "USDALL": 83.634905,
        "USDAMD": 382.719684,
        "USDANG": 1.789982,
        "USDAOA": 916.99996,
        "USDARS": 1433.993833,
        "USDAUD": 1.526193,
        "USDAWG": 1.8,
        "USDAZN": 1.696617,
        "USDBAM": 1.68722,
        "USDBBD": 2.015123,
        "USDBDT": 122.266938,
        "USDBGN": 1.690105,
        "USDBHD": 0.376967,
        "USDBIF": 2950.729164,
        "USDBMD": 1,
        "USDBND": 1.300661,
        "USDBOB": 6.913359,
        "USDBRL": 5.385732,
        "USDBSD": 1.000531,
        "USDBTC": 9.259216e-06,
        "USDBTN": 88.666802,
        "USDBWP": 13.407465,
        "USDBYN": 3.410428,
        "USDBYR": 19600,
        "USDBZD": 2.012241,
        "USDCAD": 1.398615,
        "USDCDF": 2226.000224,
        "USDCHF": 0.80175,
        "USDCLF": 0.024,
        "USDCLP": 941.549774,
        "USDCNY": 7.09905,
        "USDCNH": 7.113985,
        "USDCOP": 3869.27,
        "USDCRC": 502.508228,
        "USDCUC": 1,
        "USDCUP": 26.5,
        "USDCVE": 95.122866,
        "USDCZK": 21.05365,
        "USDDJF": 178.165208,
        "USDDKK": 6.45839,
        "USDDOP": 64.217532,
        "USDDZD": 129.969554,
        "USDEGP": 47.22795,
        "USDERN": 15,
        "USDETB": 153.771939,
        "USDEUR": 0.86496,
        "USDFJD": 2.269696,
        "USDFKP": 0.755171,
        "USDGBP": 0.76095,
        "USDGEL": 2.725005,
        "USDGGP": 0.755171,
        "USDGHS": 10.900574,
        "USDGIP": 0.755171,
        "USDGMD": 72.501751,
        "USDGNF": 8684.549921,
        "USDGTQ": 7.667489,
        "USDGYD": 209.315867,
        "USDHKD": 7.769265,
        "USDHNL": 26.307276,
        "USDHRK": 6.513499,
        "USDHTG": 130.919568,
        "USDHUF": 336.202025,
        "USDIDR": 16661.25,
        "USDILS": 3.25222,
        "USDIMP": 0.755171,
        "USDINR": 88.65575,
        "USDIQD": 1310.662233,
        "USDIRR": 42062.501748,
        "USDISK": 125.259477,
        "USDJEP": 0.755171,
        "USDJMD": 159.896824,
        "USDJOD": 0.709013,
        "USDJPY": 154.188498,
        "USDKES": 129.202614,
        "USDKGS": 87.450122,
        "USDKHR": 4021.80852,
        "USDKMF": 423.000032,
        "USDKPW": 900.015563,
        "USDKRW": 1431.075036,
        "USDKWD": 0.30689,
        "USDKYD": 0.833761,
        "USDKZT": 530.630907,
        "USDLAK": 21716.607503,
        "USDLBP": 89595.024176,
        "USDLKR": 304.369204,
        "USDLRD": 183.090998,
        "USDLSL": 17.306717,
        "USDLTL": 2.95274,
        "USDLVL": 0.60489,
        "USDLYD": 5.445205,
        "USDMAD": 9.261852,
        "USDMDL": 16.983191,
        "USDMGA": 4474.618381,
        "USDMKD": 53.284732,
        "USDMMK": 2099.25381,
        "USDMNT": 3603.679513,
        "USDMOP": 8.004796,
        "USDMRU": 39.801411,
        "USDMUR": 45.489954,
        "USDMVR": 15.310166,
        "USDMWK": 1734.895898,
        "USDMXN": 18.544075,
        "USDMYR": 4.203327,
        "USDMZN": 63.910158,
        "USDNAD": 17.306642,
        "USDNGN": 1448.959637,
        "USDNIO": 36.818972,
        "USDNOK": 10.050895,
        "USDNPR": 141.867055,
        "USDNZD": 1.741326,
        "USDOMR": 0.384521,
        "USDPAB": 1.000686,
        "USDPEN": 3.394023,
        "USDPGK": 4.218481,
        "USDPHP": 58.871968,
        "USDPKR": 283.07121,
        "USDPLN": 3.67282,
        "USDPYG": 7085.150343,
        "USDQAR": 3.646873,
        "USDRON": 4.398798,
        "USDRSD": 101.39699,
        "USDRUB": 79.850697,
        "USDRWF": 1453.237348,
        "USDSAR": 3.750303,
        "USDSBD": 8.230592,
        "USDSCR": 13.849629,
        "USDSDG": 601.506225,
        "USDSEK": 9.434895,
        "USDSGD": 1.30084,
        "USDSHP": 0.750259,
        "USDSLE": 23.14974,
        "USDSLL": 20969.499529,
        "USDSOS": 571.771171,
        "USDSRD": 38.75505,
        "USDSTD": 20697.981008,
        "USDSTN": 21.135539,
        "USDSVC": 8.754427,
        "USDSYP": 11056.780826,
        "USDSZL": 17.30425,
        "USDTHB": 32.405505,
        "USDTJS": 9.209588,
        "USDTMT": 3.51,
        "USDTND": 2.942843,
        "USDTOP": 2.3421,
        "USDTRY": 41.97628,
        "USDTTD": 6.773695,
        "USDTWD": 30.713296,
        "USDTZS": 2459.859013,
        "USDUAH": 41.990191,
        "USDUGX": 3480.893904,
        "USDUYU": 39.915975,
        "USDUZS": 11996.359511,
        "USDVES": 219.35135,
        "USDVND": 26330,
        "USDVUV": 121.65745,
        "USDWST": 2.790192,
        "USDXAF": 565.880191,
        "USDXAG": 0.020514,
        "USDXAU": 0.00025,
        "USDXCD": 2.70255,
        "USDXCG": 1.803132,
        "USDXDR": 0.700447,
        "USDXOF": 565.87775,
        "USDXPF": 102.882629,
        "USDYER": 238.650392,
        "USDZAR": 17.29389,
        "USDZMK": 9001.220523,
        "USDZMW": 22.085826,
        "USDZWL": 321.999592
    }
}