{
    "success": true,
    "terms": "https://currencylayer.com/terms",
    "privacy": "https://currencylayer.com/privacy",
    "timestamp": 1771260066,
    "source": "USD",
    "quotes": {
        "USDAED": 3.672497,
        "USDAFN": 63.499162,
        "USDALL": 81.359706,
        "USDAMD": 377.669981,
        "USDANG": 1.789731,
        "USDAOA": 917.000033,
        "USDARS": 1399.250099,
        "USDAUD": 1.41405,
        "USDAWG": 1.8,
        "USDAZN": 1.7053,
        "USDBAM": 1.649288,
        "USDBBD": 2.014597,
        "USDBDT": 122.343139,
        "USDBGN": 1.647646,
        "USDBHD": 0.376969,
        "USDBIF": 2957.216162,
        "USDBMD": 1,
        "USDBND": 1.262391,
        "USDBOB": 6.936826,
        "USDBRL": 5.236502,
        "USDBSD": 1.000215,
        "USDBTC": 1.4782414e-05,
        "USDBTN": 90.651814,
        "USDBWP": 13.147587,
        "USDBYN": 2.851806,
        "USDBYR": 19600,
        "USDBZD": 2.01173,
        "USDCAD": 1.36317,
        "USDCDF": 2254.999629,
        "USDCHF": 0.769403,
        "USDCLF": 0.021852,
        "USDCLP": 862.830106,
        "USDCNY": 6.90865,
        "USDCNH": 6.88611,
        "USDCOP": 3664.04,
        "USDCRC": 482.356463,
        "USDCUC": 1,
        "USDCUP": 26.5,
        "USDCVE": 92.984328,
        "USDCZK": 20.45995,
        "USDDJF": 178.117714,
        "USDDKK": 6.302285,
        "USDDOP": 62.267834,
        "USDDZD": 129.698534,
        "USDEGP": 46.689298,
        "USDERN": 15,
        "USDETB": 155.595546,
        "USDEUR": 0.84359,
        "USDFJD": 2.19355,
        "USDFKP": 0.732816,
        "USDGBP": 0.733635,
        "USDGEL": 2.674941,
        "USDGGP": 0.732816,
        "USDGHS": 10.998065,
        "USDGIP": 0.732816,
        "USDGMD": 73.49681,
        "USDGNF": 8779.393597,
        "USDGTQ": 7.672166,
        "USDGYD": 209.268496,
        "USDHKD": 7.81565,
        "USDHNL": 26.434315,
        "USDHRK": 6.355701,
        "USDHTG": 130.927735,
        "USDHUF": 318.457498,
        "USDIDR": 16824,
        "USDILS": 3.09454,
        "USDIMP": 0.732816,
        "USDINR": 90.81045,
        "USDIQD": 1310.373615,
        "USDIRR": 42125.000158,
        "USDISK": 122.319901,
        "USDJEP": 0.732816,
        "USDJMD": 156.445404,
        "USDJOD": 0.708994,
        "USDJPY": 153.495504,
        "USDKES": 129.030327,
        "USDKGS": 87.449862,
        "USDKHR": 4019.918286,
        "USDKMF": 415.000178,
        "USDKPW": 900.007411,
        "USDKRW": 1443.970328,
        "USDKWD": 0.30662,
        "USDKYD": 0.833583,
        "USDKZT": 491.472326,
        "USDLAK": 21429.444826,
        "USDLBP": 89572.077295,
        "USDLKR": 309.382761,
        "USDLRD": 186.044551,
        "USDLSL": 15.971902,
        "USDLTL": 2.95274,
        "USDLVL": 0.60489,
        "USDLYD": 6.306895,
        "USDMAD": 9.144787,
        "USDMDL": 16.969334,
        "USDMGA": 4364.820023,
        "USDMKD": 51.995326,
        "USDMMK": 2099.655078,
        "USDMNT": 3565.56941,
        "USDMOP": 8.053919,
        "USDMRU": 39.920057,
        "USDMUR": 45.930091,
        "USDMVR": 15.404966,
        "USDMWK": 1734.459394,
        "USDMXN": 17.171055,
        "USDMYR": 3.903338,
        "USDMZN": 63.909586,
        "USDNAD": 15.971902,
        "USDNGN": 1351.890292,
        "USDNIO": 36.809195,
        "USDNOK": 9.49805,
        "USDNPR": 145.042565,
        "USDNZD": 1.657625,
        "USDOMR": 0.384495,
        "USDPAB": 1.000299,
        "USDPEN": 3.354739,
        "USDPGK": 4.296496,
        "USDPHP": 57.960283,
        "USDPKR": 279.643967,
        "USDPLN": 3.55435,
        "USDPYG": 6537.953948,
        "USDQAR": 3.645586,
        "USDRON": 4.298303,
        "USDRSD": 99.061996,
        "USDRUB": 76.748031,
        "USDRWF": 1460.89919,
        "USDSAR": 3.750211,
        "USDSBD": 8.045182,
        "USDSCR": 13.974186,
        "USDSDG": 601.503947,
        "USDSEK": 8.945835,
        "USDSGD": 1.26257,
        "USDSHP": 0.750259,
        "USDSLE": 24.450109,
        "USDSLL": 20969.49935,
        "USDSOS": 570.647935,
        "USDSRD": 37.792012,
        "USDSTD": 20697.981008,
        "USDSTN": 20.660373,
        "USDSVC": 8.752409,
        "USDSYP": 11059.574895,
        "USDSZL": 15.964987,
        "USDTHB": 31.111005,
        "USDTJS": 9.437321,
        "USDTMT": 3.5,
        "USDTND": 2.884863,
        "USDTOP": 2.40776,
        "USDTRY": 43.708197,
        "USDTTD": 6.782505,
        "USDTWD": 31.370998,
        "USDTZS": 2609.33036,
        "USDUAH": 43.230257,
        "USDUGX": 3540.934945,
        "USDUYU": 38.757173,
        "USDUZS": 12224.194562,
        "USDVES": 392.73007,
        "USDVND": 25970,
        "USDVUV": 119.078186,
        "USDWST": 2.712216,
        "USDXAF": 553.155767,
        "USDXAG": 0.013079,
        "USDXAU": 0.0002,
        "USDXCD": 2.70255,
        "USDXCG": 1.802681,
        "USDXDR": 0.687563,
        "USDXOF": 553.155767,
        "USDXPF": 100.569636,
        "USDYER": 238.34999,
        "USDZAR": 15.98271,
        "USDZMK": 9001.145196,
        "USDZMW": 18.381829,
        "USDZWL": 321.999592
    }
}