{
    "success": true,
    "terms": "https://currencylayer.com/terms",
    "privacy": "https://currencylayer.com/privacy",
    "timestamp": 1762824308,
    "source": "USD",
    "quotes": {
        "USDAED": 3.6725,
        "USDAFN": 66.40135,
        "USDALL": 83.577028,
        "USDAMD": 382.730415,
        "USDANG": 1.789982,
        "USDAOA": 917.000282,
        "USDARS": 1419.988801,
        "USDAUD": 1.531511,
        "USDAWG": 1.8075,
        "USDAZN": 1.699594,
        "USDBAM": 1.692008,
        "USDBBD": 2.014958,
        "USDBDT": 122.146716,
        "USDBGN": 1.69225,
        "USDBHD": 0.377002,
        "USDBIF": 2946.886653,
        "USDBMD": 1,
        "USDBND": 1.303554,
        "USDBOB": 6.938286,
        "USDBRL": 5.291903,
        "USDBSD": 1.000502,
        "USDBTC": 9.34776e-06,
        "USDBTN": 88.679433,
        "USDBWP": 13.388763,
        "USDBYN": 3.410355,
        "USDBYR": 19600,
        "USDBZD": 2.012017,
        "USDCAD": 1.403101,
        "USDCDF": 2148.00003,
        "USDCHF": 0.805795,
        "USDCLF": 0.023909,
        "USDCLP": 937.939898,
        "USDCNY": 7.11965,
        "USDCNH": 7.12478,
        "USDCOP": 3753.72,
        "USDCRC": 502.320833,
        "USDCUC": 1,
        "USDCUP": 26.5,
        "USDCVE": 95.624995,
        "USDCZK": 21.026597,
        "USDDJF": 178.159229,
        "USDDKK": 6.46486,
        "USDDOP": 64.250211,
        "USDDZD": 130.349814,
        "USDEGP": 47.256896,
        "USDERN": 15,
        "USDETB": 153.632223,
        "USDEUR": 0.865791,
        "USDFJD": 2.280104,
        "USDFKP": 0.760102,
        "USDGBP": 0.759905,
        "USDGEL": 2.704994,
        "USDGGP": 0.760102,
        "USDGHS": 10.944671,
        "USDGIP": 0.760102,
        "USDGMD": 73.000119,
        "USDGNF": 8684.668161,
        "USDGTQ": 7.66845,
        "USDGYD": 209.299207,
        "USDHKD": 7.77345,
        "USDHNL": 26.322961,
        "USDHRK": 6.524301,
        "USDHTG": 130.986988,
        "USDHUF": 332.18297,
        "USDIDR": 16697,
        "USDILS": 3.23525,
        "USDIMP": 0.760102,
        "USDINR": 88.68265,
        "USDIQD": 1310.523812,
        "USDIRR": 42100.000199,
        "USDISK": 126.570057,
        "USDJEP": 0.760102,
        "USDJMD": 161.038579,
        "USDJOD": 0.709026,
        "USDJPY": 154.4185,
        "USDKES": 129.19885,
        "USDKGS": 87.450164,
        "USDKHR": 4015.000234,
        "USDKMF": 420.999854,
        "USDKPW": 900.001961,
        "USDKRW": 1464.119695,
        "USDKWD": 0.30716,
        "USDKYD": 0.833687,
        "USDKZT": 524.097063,
        "USDLAK": 21722.392837,
        "USDLBP": 89583.978546,
        "USDLKR": 304.200009,
        "USDLRD": 183.077329,
        "USDLSL": 17.192699,
        "USDLTL": 2.95274,
        "USDLVL": 0.60489,
        "USDLYD": 5.459328,
        "USDMAD": 9.261661,
        "USDMDL": 16.981703,
        "USDMGA": 4494.683382,
        "USDMKD": 53.222318,
        "USDMMK": 2099.688142,
        "USDMNT": 3580.599313,
        "USDMOP": 8.009828,
        "USDMRU": 39.728682,
        "USDMUR": 45.859581,
        "USDMVR": 15.405009,
        "USDMWK": 1734.887222,
        "USDMXN": 18.39024,
        "USDMYR": 4.160502,
        "USDMZN": 63.959586,
        "USDNAD": 17.192699,
        "USDNGN": 1436.610151,
        "USDNIO": 36.813372,
        "USDNOK": 10.139695,
        "USDNPR": 141.895686,
        "USDNZD": 1.773445,
        "USDOMR": 0.384501,
        "USDPAB": 1.000428,
        "USDPEN": 3.376575,
        "USDPGK": 4.223805,
        "USDPHP": 58.910219,
        "USDPKR": 282.888599,
        "USDPLN": 3.66715,
        "USDPYG": 7087.087607,
        "USDQAR": 3.64632,
        "USDRON": 4.4023,
        "USDRSD": 101.448522,
        "USDRUB": 81.253144,
        "USDRWF": 1454.218254,
        "USDSAR": 3.750579,
        "USDSBD": 8.230592,
        "USDSCR": 13.741165,
        "USDSDG": 600.508457,
        "USDSEK": 9.519375,
        "USDSGD": 1.303675,
        "USDSHP": 0.750259,
        "USDSLE": 23.19801,
        "USDSLL": 20969.499529,
        "USDSOS": 570.768552,
        "USDSRD": 38.496503,
        "USDSTD": 20697.981008,
        "USDSTN": 21.196889,
        "USDSVC": 8.752974,
        "USDSYP": 11056.839565,
        "USDSZL": 17.189528,
        "USDTHB": 32.360026,
        "USDTJS": 9.26848,
        "USDTMT": 3.51,
        "USDTND": 2.953357,
        "USDTOP": 2.342104,
        "USDTRY": 42.23617,
        "USDTTD": 6.785761,
        "USDTWD": 30.983302,
        "USDTZS": 2455.60639,
        "USDUAH": 42.069631,
        "USDUGX": 3511.534252,
        "USDUYU": 39.804309,
        "USDUZS": 12020.018946,
        "USDVES": 228.194037,
        "USDVND": 26300,
        "USDVUV": 122.518583,
        "USDWST": 2.820889,
        "USDXAF": 567.53013,
        "USDXAG": 0.019702,
        "USDXAU": 0.000242,
        "USDXCD": 2.70255,
        "USDXCG": 1.802933,
        "USDXDR": 0.705825,
        "USDXOF": 567.52522,
        "USDXPF": 103.174569,
        "USDYER": 238.497116,
        "USDZAR": 17.155145,
        "USDZMK": 9001.196773,
        "USDZMW": 22.634213,
        "USDZWL": 321.999592
    }
}