{
    "success": true,
    "terms": "https://currencylayer.com/terms",
    "privacy": "https://currencylayer.com/privacy",
    "timestamp": 1757002928,
    "source": "USD",
    "quotes": {
        "USDAED": 3.672979,
        "USDAFN": 69.497579,
        "USDALL": 83.949785,
        "USDAMD": 382.250249,
        "USDANG": 1.789783,
        "USDAOA": 916.99969,
        "USDARS": 1362.743201,
        "USDAUD": 1.53611,
        "USDAWG": 1.8025,
        "USDAZN": 1.70123,
        "USDBAM": 1.679476,
        "USDBBD": 2.015405,
        "USDBDT": 121.773927,
        "USDBGN": 1.680095,
        "USDBHD": 0.376955,
        "USDBIF": 2942.5,
        "USDBMD": 1,
        "USDBND": 1.289877,
        "USDBOB": 6.914377,
        "USDBRL": 5.466803,
        "USDBSD": 1.000661,
        "USDBTC": 9.12746e-06,
        "USDBTN": 88.144573,
        "USDBWP": 14.398942,
        "USDBYN": 3.379733,
        "USDBYR": 19600,
        "USDBZD": 2.012486,
        "USDCAD": 1.383535,
        "USDCDF": 2864.999975,
        "USDCHF": 0.806098,
        "USDCLF": 0.024735,
        "USDCLP": 970.289752,
        "USDCNY": 7.142097,
        "USDCNH": 7.14168,
        "USDCOP": 3994.36,
        "USDCRC": 505.869321,
        "USDCUC": 1,
        "USDCUP": 26.5,
        "USDCVE": 94.650507,
        "USDCZK": 20.999495,
        "USDDJF": 178.19206,
        "USDDKK": 6.412575,
        "USDDOP": 63.374979,
        "USDDZD": 129.863023,
        "USDEGP": 48.549301,
        "USDERN": 15,
        "USDETB": 142.625038,
        "USDEUR": 0.859005,
        "USDFJD": 2.280024,
        "USDFKP": 0.743571,
        "USDGBP": 0.744704,
        "USDGEL": 2.695008,
        "USDGGP": 0.743571,
        "USDGHS": 12.049637,
        "USDGIP": 0.743571,
        "USDGMD": 72.000165,
        "USDGNF": 8659.999776,
        "USDGTQ": 7.674341,
        "USDGYD": 209.260388,
        "USDHKD": 7.80087,
        "USDHNL": 26.150144,
        "USDHRK": 6.4733,
        "USDHTG": 130.885422,
        "USDHUF": 337.471973,
        "USDIDR": 16460.5,
        "USDILS": 3.361398,
        "USDIMP": 0.743571,
        "USDINR": 88.185601,
        "USDIQD": 1310,
        "USDIRR": 42074.999817,
        "USDISK": 123.010121,
        "USDJEP": 0.743571,
        "USDJMD": 160.210557,
        "USDJOD": 0.709014,
        "USDJPY": 148.651498,
        "USDKES": 129.483931,
        "USDKGS": 87.449647,
        "USDKHR": 4003.999697,
        "USDKMF": 422.501945,
        "USDKPW": 899.978428,
        "USDKRW": 1395.025038,
        "USDKWD": 0.30596,
        "USDKYD": 0.833899,
        "USDKZT": 540.278052,
        "USDLAK": 21685.000099,
        "USDLBP": 89550.000229,
        "USDLKR": 302.216345,
        "USDLRD": 200.875029,
        "USDLSL": 17.660214,
        "USDLTL": 2.95274,
        "USDLVL": 0.60489,
        "USDLYD": 5.420068,
        "USDMAD": 9.074991,
        "USDMDL": 16.770714,
        "USDMGA": 4480.00003,
        "USDMKD": 52.836767,
        "USDMMK": 2099.392875,
        "USDMNT": 3596.745904,
        "USDMOP": 8.038865,
        "USDMRU": 39.959737,
        "USDMUR": 46.159676,
        "USDMVR": 15.409899,
        "USDMWK": 1737.99964,
        "USDMXN": 18.768798,
        "USDMYR": 4.224993,
        "USDMZN": 63.902967,
        "USDNAD": 17.659778,
        "USDNGN": 1525.550146,
        "USDNIO": 36.63004,
        "USDNOK": 10.1075,
        "USDNPR": 141.031146,
        "USDNZD": 1.71346,
        "USDOMR": 0.384497,
        "USDPAB": 1.000661,
        "USDPEN": 3.532495,
        "USDPGK": 4.231975,
        "USDPHP": 57.119672,
        "USDPKR": 281.749803,
        "USDPLN": 3.652268,
        "USDPYG": 7212.351764,
        "USDQAR": 3.640603,
        "USDRON": 4.360103,
        "USDRSD": 100.665019,
        "USDRUB": 81.296876,
        "USDRWF": 1445,
        "USDSAR": 3.752146,
        "USDSBD": 8.223823,
        "USDSCR": 14.695019,
        "USDSDG": 600.499278,
        "USDSEK": 9.481835,
        "USDSGD": 1.290105,
        "USDSHP": 0.785843,
        "USDSLE": 23.290014,
        "USDSLL": 20969.49797,
        "USDSOS": 571.495554,
        "USDSRD": 38.941995,
        "USDSTD": 20697.981008,
        "USDSTN": 21.35,
        "USDSVC": 8.755426,
        "USDSYP": 13001.944331,
        "USDSZL": 17.660505,
        "USDTHB": 32.269792,
        "USDTJS": 9.481078,
        "USDTMT": 3.51,
        "USDTND": 2.879,
        "USDTOP": 2.342099,
        "USDTRY": 41.163703,
        "USDTTD": 6.786429,
        "USDTWD": 30.713965,
        "USDTZS": 2504.999762,
        "USDUAH": 41.349134,
        "USDUGX": 3519.874971,
        "USDUYU": 40.102188,
        "USDUZS": 12384.999791,
        "USDVES": 151.783895,
        "USDVND": 26390,
        "USDVUV": 120.199795,
        "USDWST": 2.772418,
        "USDXAF": 563.280465,
        "USDXAG": 0.024528,
        "USDXAU": 0.000281,
        "USDXCD": 2.70255,
        "USDXCG": 1.803388,
        "USDXDR": 0.699693,
        "USDXOF": 563.497192,
        "USDXPF": 102.750003,
        "USDYER": 240.149995,
        "USDZAR": 17.787465,
        "USDZMK": 9001.20203,
        "USDZMW": 23.810464,
        "USDZWL": 321.999592
    }
}