{
    "success": true,
    "terms": "https://currencylayer.com/terms",
    "privacy": "https://currencylayer.com/privacy",
    "timestamp": 1758763148,
    "source": "USD",
    "quotes": {
        "USDAED": 3.672498,
        "USDAFN": 67.475889,
        "USDALL": 82.482125,
        "USDAMD": 382.958801,
        "USDANG": 1.790403,
        "USDAOA": 917.000025,
        "USDARS": 1337.494294,
        "USDAUD": 1.517577,
        "USDAWG": 1.40625,
        "USDAZN": 1.698182,
        "USDBAM": 1.664787,
        "USDBBD": 2.014726,
        "USDBDT": 121.739352,
        "USDBGN": 1.66535,
        "USDBHD": 0.37692,
        "USDBIF": 2986.078304,
        "USDBMD": 1,
        "USDBND": 1.287725,
        "USDBOB": 6.912666,
        "USDBRL": 5.331298,
        "USDBSD": 1.00034,
        "USDBTC": 8.829126e-06,
        "USDBTN": 88.793837,
        "USDBWP": 13.315458,
        "USDBYN": 3.388236,
        "USDBYR": 19600,
        "USDBZD": 2.011832,
        "USDCAD": 1.389425,
        "USDCDF": 2808.99989,
        "USDCHF": 0.794805,
        "USDCLF": 0.02428,
        "USDCLP": 952.510239,
        "USDCNY": 7.13215,
        "USDCNH": 7.13292,
        "USDCOP": 3886.99,
        "USDCRC": 504.35619,
        "USDCUC": 1,
        "USDCUP": 26.5,
        "USDCVE": 93.858529,
        "USDCZK": 20.69535,
        "USDDJF": 178.132448,
        "USDDKK": 6.35565,
        "USDDOP": 61.935791,
        "USDDZD": 129.513933,
        "USDEGP": 48.157704,
        "USDERN": 15,
        "USDETB": 145.40711,
        "USDEUR": 0.85158,
        "USDFJD": 2.255399,
        "USDFKP": 0.739839,
        "USDGBP": 0.74339,
        "USDGEL": 2.698512,
        "USDGGP": 0.739839,
        "USDGHS": 12.354443,
        "USDGIP": 0.739839,
        "USDGMD": 73.999774,
        "USDGNF": 8679.886107,
        "USDGTQ": 7.662581,
        "USDGYD": 209.286687,
        "USDHKD": 7.77927,
        "USDHNL": 26.253607,
        "USDHRK": 6.415902,
        "USDHTG": 130.892593,
        "USDHUF": 333.379994,
        "USDIDR": 16717.75,
        "USDILS": 3.356185,
        "USDIMP": 0.739839,
        "USDINR": 88.744404,
        "USDIQD": 1310.430242,
        "USDIRR": 42075.000409,
        "USDISK": 121.100356,
        "USDJEP": 0.739839,
        "USDJMD": 159.95778,
        "USDJOD": 0.708962,
        "USDJPY": 148.665993,
        "USDKES": 129.239978,
        "USDKGS": 87.450461,
        "USDKHR": 4008.393025,
        "USDKMF": 419.999977,
        "USDKPW": 900.036397,
        "USDKRW": 1400.630267,
        "USDKWD": 0.30544,
        "USDKYD": 0.833585,
        "USDKZT": 541.945259,
        "USDLAK": 21664.872043,
        "USDLBP": 89579.502894,
        "USDLKR": 302.594899,
        "USDLRD": 180.05618,
        "USDLSL": 17.321172,
        "USDLTL": 2.95274,
        "USDLVL": 0.60489,
        "USDLYD": 5.400068,
        "USDMAD": 9.059244,
        "USDMDL": 16.680215,
        "USDMGA": 4426.285325,
        "USDMKD": 52.434234,
        "USDMMK": 2099.371169,
        "USDMNT": 3594.923948,
        "USDMOP": 8.01367,
        "USDMRU": 39.820052,
        "USDMUR": 45.300902,
        "USDMVR": 15.310477,
        "USDMWK": 1734.593122,
        "USDMXN": 18.42035,
        "USDMYR": 4.216988,
        "USDMZN": 63.91005,
        "USDNAD": 17.321172,
        "USDNGN": 1490.450226,
        "USDNIO": 36.815247,
        "USDNOK": 9.942535,
        "USDNPR": 142.073163,
        "USDNZD": 1.72021,
        "USDOMR": 0.384496,
        "USDPAB": 1.00034,
        "USDPEN": 3.501602,
        "USDPGK": 4.187983,
        "USDPHP": 57.755497,
        "USDPKR": 283.608529,
        "USDPLN": 3.633445,
        "USDPYG": 7115.25366,
        "USDQAR": 3.646578,
        "USDRON": 4.323301,
        "USDRSD": 99.807026,
        "USDRUB": 83.748552,
        "USDRWF": 1450.447306,
        "USDSAR": 3.750745,
        "USDSBD": 8.223773,
        "USDSCR": 15.134629,
        "USDSDG": 601.49205,
        "USDSEK": 9.40128,
        "USDSGD": 1.28766,
        "USDSHP": 0.785843,
        "USDSLE": 23.300282,
        "USDSLL": 20969.503664,
        "USDSOS": 571.666908,
        "USDSRD": 38.117502,
        "USDSTD": 20697.981008,
        "USDSTN": 20.854791,
        "USDSVC": 8.752942,
        "USDSYP": 13002.670751,
        "USDSZL": 17.314436,
        "USDTHB": 32.107959,
        "USDTJS": 9.378107,
        "USDTMT": 3.51,
        "USDTND": 2.907644,
        "USDTOP": 2.342097,
        "USDTRY": 41.4754,
        "USDTTD": 6.790063,
        "USDTWD": 30.396799,
        "USDTZS": 2465.000226,
        "USDUAH": 41.466547,
        "USDUGX": 3495.914198,
        "USDUYU": 39.896153,
        "USDUZS": 12174.786454,
        "USDVES": 169.763603,
        "USDVND": 26419,
        "USDVUV": 119.321226,
        "USDWST": 2.679003,
        "USDXAF": 558.351563,
        "USDXAG": 0.022767,
        "USDXAU": 0.000267,
        "USDXCD": 2.70255,
        "USDXCG": 1.802852,
        "USDXDR": 0.694416,
        "USDXOF": 558.356316,
        "USDXPF": 101.514719,
        "USDYER": 239.249902,
        "USDZAR": 17.322296,
        "USDZMK": 9001.19768,
        "USDZMW": 23.662751,
        "USDZWL": 321.999592
    }
}